nagios_sql-0.9.0.dist-info/DESCRIPTION.rst
nagios_sql-0.9.0.dist-info/METADATA
nagios_sql-0.9.0.dist-info/RECORD
nagios_sql-0.9.0.dist-info/WHEEL
nagios_sql-0.9.0.dist-info/entry_points.txt
nagios_sql-0.9.0.dist-info/metadata.json
nagios_sql-0.9.0.dist-info/top_level.txt
src/__init__.py
src/nagios_sql.py
src/version.py
