Metadata-Version: 2.0
Name: nagios-sql
Version: 0.9.0
Summary: Nagios plugin with sqlchecks
Home-page: https://github.com/pablodav/nagios_sql
Author: Pablo Estigarribia
Author-email: pablodav@gmail.com
License: MIT
Platform: UNKNOWN
Classifier: Development Status :: 5 - Production/Stable
Classifier: Intended Audience :: System Administrators
Classifier: License :: OSI Approved :: MIT License
Classifier: Programming Language :: Python :: 3
Classifier: Programming Language :: Python :: 3 :: Only
Classifier: Programming Language :: SQL
Classifier: Topic :: System :: Monitoring
Classifier: Topic :: Database :: Database Engines/Servers
Classifier: Topic :: System :: Systems Administration
Requires-Dist: pymssql (<3.0)
Requires-Dist: rstcheck (>=3.1)
